main.py
demozodiurjnb-0.1.0.dist-info/METADATA
demozodiurjnb-0.1.0.dist-info/WHEEL
demozodiurjnb-0.1.0.dist-info/top_level.txt
demozodiurjnb-0.1.0.dist-info/RECORD
